lbst.py
lbst-0.2.0.dist-info/LICENSE
lbst-0.2.0.dist-info/WHEEL
lbst-0.2.0.dist-info/METADATA
lbst-0.2.0.dist-info/RECORD
