Metadata-Version: 2.1
Name: lbst
Version: 0.2.0
Summary: Immutable Log-Balanced Search Tree
Home-page: https://github.com/amirouche/lbst
License: CC0
Author: Amirouche
Author-email: amirouche@hyper.dev
Requires-Python: >=3.7,<4.0
Classifier: License :: Other/Proprietary License
Classifier: Programming Language :: Python :: 3
Classifier: Programming Language :: Python :: 3.10
Classifier: Programming Language :: Python :: 3.7
Classifier: Programming Language :: Python :: 3.8
Classifier: Programming Language :: Python :: 3.9
